francine/__init__.py
francine/cli.py
francine/config.py
francine/models/__init__.py
francine/models/task.py
francine/repositories/__init__.py
francine/repositories/base.py
francine/repositories/tinydb.py
francine/services/__init__.py
francine/services/task.py
francine-0.0.4.dist-info/LICENSE
francine-0.0.4.dist-info/METADATA
francine-0.0.4.dist-info/WHEEL
francine-0.0.4.dist-info/entry_points.txt
francine-0.0.4.dist-info/RECORD
